har2tree/__init__.py
har2tree/har2tree.py
har2tree/helper.py
har2tree/nodes.py
har2tree/parser.py
har2tree/py.typed
har2tree-1.36.2.dist-info/METADATA
har2tree-1.36.2.dist-info/WHEEL
har2tree-1.36.2.dist-info/licenses/LICENSE
har2tree-1.36.2.dist-info/RECORD
