Metadata-Version: 2.4
Name: har2tree
Version: 1.36.2
Summary: HTTP Archive (HAR) to ETE Toolkit generator
License-Expression: BSD-3-Clause
License-File: LICENSE
Author: Raphaël Vinot
Author-email: raphael.vinot@circl.lu
Requires-Python: >=3.10,<3.15
Classifier: Intended Audience :: Information Technology
Classifier: Intended Audience :: Science/Research
Classifier: Intended Audience :: Telecommunications Industry
Classifier: Operating System :: POSIX :: Linux
Classifier: Programming Language :: Python :: 3
Classifier: Programming Language :: Python :: 3.10
Classifier: Programming Language :: Python :: 3.11
Classifier: Programming Language :: Python :: 3.12
Classifier: Programming Language :: Python :: 3.13
Classifier: Programming Language :: Python :: 3.14
Classifier: Topic :: Internet
Classifier: Topic :: Security
Provides-Extra: docs
Requires-Dist: Sphinx (>=9.1.0) ; (python_version >= "3.12") and (extra == "docs")
Requires-Dist: beautifulsoup4[charset-normalizer,lxml] (>=4.14.3)
Requires-Dist: ete3 (>=3.1.3)
Requires-Dist: filetype (>=1.2.0)
Requires-Dist: json-stream (>=2.3.3,<3.0.0)
Requires-Dist: legacy-cgi (>=2.6.4) ; python_version >= "3.13" and python_version < "4.0"
Requires-Dist: multipart (>=1.3.0,<2.0.0)
Requires-Dist: numpy (>=2.2,<2.3) ; python_version < "3.11"
Requires-Dist: numpy (>=2.4.1) ; python_version >= "3.11" and python_version < "4.0"
Requires-Dist: publicsuffixlist (>=1.0.2.20260126)
Requires-Dist: requests-toolbelt (>=1.0.0,<2.0.0)
Requires-Dist: six (>=1.17.0) ; extra == "docs"
Requires-Dist: tinycss2 (>=1.5.1)
Requires-Dist: w3lib (>=2.3.1)
Project-URL: Documentation, https://har2tree.readthedocs.io/en/latest/
Project-URL: Repository, https://github.com/Lookyloo/har2tree
Project-URL: issues, https://github.com/Lookyloo/har2tree/issues
